[
  {
    "name": "development",
    "host": "172.16.128.101",
    "port": 27017,
    "user": "stockman",
    "pass": "Covage01",
    "database": "stock_manager",
    "type": "mongodb",
    "logfile": "db.log",
    "tokenSalt": "covageProd"
  }, {
    "name": "production",
    "host": "172.16.128.101",
    "port": 27017,
    "user": "stockman",
    "pass": "Covage01",
    "database": "stock_manager",
    "type": "mongodb",
    "logfile": "db.log",
    "tokenSalt": "covageProd"
  }, {
    "name": "test",
    "host": "127.0.0.1",
    "port": 27017,
    "database": "test",
    "type": "mongodb",
    "logfile": "test-db.log",
    "tokenSalt": "covageTest"
  }
]
